confident/__init__.py
confident/confident.py
confident/config_field.py
confident/config_source.py
confident/loader_manager.py
confident/loaders/__init__.py
confident/loaders/default_source_loader.py
confident/loaders/env_source_loader.py
confident/loaders/file_source_loader.py
confident/loaders/init_source_loader.py
confident/loaders/map_source_loader.py
confident/loaders/source_loader_base.py
confident/map_field.py
confident/specs.py
confident/utils.py
confident-0.2.6.dist-info/LICENSE
confident-0.2.6.dist-info/WHEEL
confident-0.2.6.dist-info/METADATA
confident-0.2.6.dist-info/RECORD
